packages/__init__.py
packages/function.py
your_package-0.1.dist-info/METADATA
your_package-0.1.dist-info/WHEEL
your_package-0.1.dist-info/top_level.txt
your_package-0.1.dist-info/RECORD
