Metadata-Version: 2.1
Name: your-package
Version: 0.1
Summary: ac library
Home-page: UNKNOWN
Author: ac
Author-email: UNKNOWN
License: MIT
Keywords: sample setuptools development
Platform: UNKNOWN
Classifier: Programming Language :: Python :: 3.6
